COPYING
LICENSE.txt
MANIFEST.in
Makefile.example
README.md
README.rst
setup.cfg
setup.py
version.py
zanata.xml
archaeological_context_records/__init__.py
archaeological_context_records/admin.py
archaeological_context_records/data_importer.py
archaeological_context_records/forms.py
archaeological_context_records/ishtar_menu.py
archaeological_context_records/models.py
archaeological_context_records/tests.py
archaeological_context_records/urls.py
archaeological_context_records/views.py
archaeological_context_records/wizards.py
archaeological_context_records/fixtures/initial_data-fr.json
archaeological_context_records/locale/django.pot
archaeological_context_records/locale/fr/LC_MESSAGES/django.mo
archaeological_context_records/locale/fr/LC_MESSAGES/django.po
archaeological_context_records/templates/ishtar/sheet_contextrecord.html
archaeological_context_records/templates/ishtar/sheet_contextrecord_pdf.html
archaeological_context_records/templates/ishtar/sheet_contextrecord_window.html
archaeological_context_records/templates/ishtar/sheet_contextrecordsource.html
archaeological_context_records/templates/ishtar/sheet_contextrecordsource_pdf.html
archaeological_context_records/templates/ishtar/sheet_contextrecordsource_window.html
archaeological_context_records/tests/MCC-context-records-example.csv
archaeological_files/__init__.py
archaeological_files/admin.py
archaeological_files/data_importer.py
archaeological_files/forms.py
archaeological_files/ishtar_menu.py
archaeological_files/models.py
archaeological_files/tests.py
archaeological_files/urls.py
archaeological_files/views.py
archaeological_files/wizards.py
archaeological_files/fixtures/initial_data-fr.json
archaeological_files/locale/django.pot
archaeological_files/locale/fr/LC_MESSAGES/django.mo
archaeological_files/locale/fr/LC_MESSAGES/django.po
archaeological_files/templates/ishtar/administrativeact_document.html
archaeological_files/templates/ishtar/sheet_file.html
ishtar.egg-info/PKG-INFO
ishtar.egg-info/SOURCES.txt
ishtar.egg-info/dependency_links.txt
ishtar.egg-info/requires.txt
ishtar.egg-info/top_level.txt
