Metadata-Version: 1.1
Name: ishtar
Version: 0.99.27
Summary: Ishtar is a database to manage the finds and documentation from archaeological operations.
Home-page: http://ishtar-archeo.net/
Author: Étienne Loks
Author-email: etienne.loks@iggdrasil.net
License: AGPL v3 licence, see COPYING
Platform: UNKNOWN
Classifier: Development Status :: 5 - Production/Stable
Classifier: Environment :: Web Environment
Classifier: Framework :: Django
Classifier: Intended Audience :: Developers
Classifier: Programming Language :: Python
Classifier: Operating System :: OS Independent
